docker/__init__.py
docker/container.py
docker/utils.py
postgre_test_container-0.0.1.dist-info/LICENSE
postgre_test_container-0.0.1.dist-info/METADATA
postgre_test_container-0.0.1.dist-info/WHEEL
postgre_test_container-0.0.1.dist-info/top_level.txt
postgre_test_container-0.0.1.dist-info/RECORD
