Metadata-Version: 2.1
Name: postgre-test-container
Version: 0.0.1
Summary: Temporary test docker container
Home-page: https://github.com/malmstine/postgre-test-container
Author: Ivan Malmstine
Author-email: ivan@malmstine.com
License: MIT
Keywords: docker,postgreSQL,postgre,test,test container
License-File: LICENSE
